{
  "Url": "http://www.baomoi.com/Anh-Thuy-quyet-dinh-bo-thi-XFactor-Viet-Nam/71/13466283.epi",
  "Time": "02/04/2014 19:49",
  "Title": "Anh Thúy quyết định bỏ thi 'X-Factor Việt Nam'",
  "Category": "Tin tức > Giải trí > Âm nhạc",
  "Description": "Anh Thúy vừa đăng status tuyên bố bỏ thi 'X-Factor Việt Nam' trên Facebook vào tối nay 2/4.",
  "Content": "<tr><td><div> <div>Một ngày sau khi chính thức thừa nhận &quot;lừa dối khán giả&quot; tại &quot;X-Factor Việt Nam&quot; , <span>Anh Thúy</span> vừa tuyên bố bỏ thi trên Facebook. Cách đây một giờ, nữ ca sỹ đăng tải một status cho biết đã xin phép BTC dừng cuộc chơi vì không muốn ảnh hưởng đến chương trình và các thí sinh khác.</div><br /><div><span><span class='storyInlinePhoto'><img src='http://k14.vcmedia.vn/k:3tcTp2m8DCNfJcBFqbRIjm0nKqWccc/Image/2014/04/01/140402musicANHTHUY01-ecce8/anh-thuy-quyet-dinh-bo-thi-xfactor-viet-nam.png' ></span><br></span></div><div><span>Status thông báo bỏ thi của Anh Thúy</span></div><br /><div>Nội dung status của <span>Anh Thúy</span>:<span> &quot;Thúy đã xin phép Ban tổ chức dừng cuộc thi tại đây mặc dù ban tổ chức vẫn dang rộng vòng tay và muốn Thúy tiếp tục niềm đam mê ca hát nhưng Thúy không muốn ảnh hưởng đến chương trình đến các bạn thí sinh khác. Lỗi lầm này hoàn toàn thuộc về mình Thúy mọi người đừng hiểu lầm là chương trình dàn dựng. Thúy chỉ muốn tìm lại cảm giác trong âm nhạc nên muốn hát trong thân phận 1 người khác để có cảm xúc hơn nhưng giờ thì nó cũng đã mất đi rồi thôi thì quay trở lại cuộc sống trước kia để ko ảnh hưởng đến ai nữa. Mọi người hãy tiếp tục ủng hộ chương trình Nhân tố bí ẩn nhé có rất nhìu tài năng âm nhạc sẽ xuất hiện trong chương trình và rất mong chương trình sẽ thành công tốt đẹp. Xin lỗi mọi người một lần nữa nha&quot;.</span></div><br /><div>Sau hơn một giờ, status này đã có hơn 500 lượt Like và gần 200 bình luận chia làm hai luồng ý kiến trái chiều: một số động viên <span>Anh Thúy</span>, số khác tiếp tục chỉ trích nữ ca sỹ vì đã lừa dối khán giả. Trước đó vào chiều nay 2/4, <span>Anh Thúy</span> cũng đã đăng một status đòi tự vẫn vì áp lực của scandal .</div> </div><br /></td></tr>",
  "KeyWords": [
    "The X Factor",
    "lừa dối",
    "Facebook",
    "ban tổ chức",
    "xin phép",
    "thí sinh",
    "tự vẫn",
    "lỗi lầm",
    "âm nhạc",
    "trái chiều",
    "ca sĩ",
    "Anh Thúy",
    "scandal"
  ],
  "Trends": [
    {
      "word": "Ballad",
      "weith": "6"
    },
    {
      "word": "cư dân mạng",
      "weith": "2"
    },
    {
      "word": "Đàm Vĩnh Hưng",
      "weith": "4"
    },
    {
      "word": "Destiny's Child",
      "weith": "4"
    },
    {
      "word": "Đông Hùng",
      "weith": "6"
    },
    {
      "word": "Elvis Phương",
      "weith": "4"
    },
    {
      "word": "fan",
      "weith": "1"
    },
    {
      "word": "Festival",
      "weith": "5"
    },
    {
      "word": "Giải Cống hiến",
      "weith": "4"
    },
    {
      "word": "hit",
      "weith": "4"
    },
    {
      "word": "Huỳnh Anh",
      "weith": "6"
    },
    {
      "word": "Kelly Rowland",
      "weith": "1"
    },
    {
      "word": "K-Pop",
      "weith": "4"
    },
    {
      "word": "live show",
      "weith": "1"
    },
    {
      "word": "Miley Cyrus",
      "weith": "4"
    },
    {
      "word": "MV",
      "weith": "1"
    },
    {
      "word": "Mỹ Tâm",
      "weith": "4"
    },
    {
      "word": "Nguyễn Đình Thanh Tâm",
      "weith": "6"
    },
    {
      "word": "Phương Linh",
      "weith": "5"
    },
    {
      "word": "Rock",
      "weith": "3"
    },
    {
      "word": "The Voice",
      "weith": "4"
    },
    {
      "word": "The X Factor",
      "weith": "5"
    },
    {
      "word": "Thu Minh",
      "weith": "6"
    },
    {
      "word": "Thủy Tiên",
      "weith": "3"
    },
    {
      "word": "Trang Pháp",
      "weith": "2"
    },
    {
      "word": "Tùng Dương",
      "weith": "5"
    },
    {
      "word": "video",
      "weith": "2"
    },
    {
      "word": "video clip",
      "weith": "1"
    },
    {
      "word": "Vietnam Idol",
      "weith": "2"
    },
    {
      "word": "Youtube",
      "weith": "5"
    }
  ]
}