{
  "Url": "http://www.baomoi.com/Cam-dao-giet-nguoi-khi-phien-toa-ket-thuc/104/13553883.epi",
  "Time": "13/04/2014 19:11",
  "Title": "Cầm dao giết người khi phiên tòa kết thúc",
  "Category": "Tin tức > Pháp luật > Hình sự",
  "Description": "Phẫn uất trước cái chết của anh trai, Hổ cầm dao đâm bị cáo ngay sau khi phiên tòa vừa kết thúc.",
  "Content": "<tr><td><div itemprop='articleBody'> <p>Công an tỉnh Sơn La đang hoàn tất hồ sơ để khởi tố bị can Hoàng Mạnh Hổ (48 tuổi, ở Mỹ Đức, Hà Nội) về hành vi Giết người.</p> <p>Trước đó, ngày 10/4, TAND tỉnh Sơn La mở phiên xử sơ thẩm với bị cáo Đào Văn Quỳnh (24 tuổi, ở huyện Ứng Hòa, Hà Nội) tội Giết người. Theo cáo trạng, cuối năm 2013, Quỳnh và và Hoàng Mạnh Hùng (anh trai Hổ) có mâu thuẫn. Trong lúc đánh nhau, nam thanh niên 24 tuổi cầm dao đâm chết Hùng.</p> <p>Phẫn uất trước cái chết của anh trai mình nên sau phiên xử Quỳnh được dẫn giải về trại giam, Hổ cầm dao xông tới đâm vào bụng người này.</p> <p>Cảnh sát đã kịp khống chế hung thủ. Nạn nhân được đưa vào bệnh viện Đa khoa tỉnh Sơn La cấp cứu kịp nên qua cơn nguy kịch.</p>  </div> <p itemprop='author' itemscope='' itemtype='http://schema.org/Person'> Lê Tú </p><br /></td></tr>",
  "KeyWords": [
    "hổ",
    "Sơn La",
    "giết người",
    "phẫn uất",
    "anh trai",
    "bị cáo",
    "phiên tòa",
    "cái chết",
    "Ứng Hòa",
    "dẫn giải",
    "đâm chết",
    "Mỹ Đức",
    "Hà Nội",
    "tòa án nhân dân"
  ],
  "Trends": [
    {
      "word": "bào chữa",
      "weith": "4"
    },
    {
      "word": "bắt",
      "weith": "6"
    },
    {
      "word": "bắt giữ",
      "weith": "1"
    },
    {
      "word": "bộ luật hình sự",
      "weith": "3"
    },
    {
      "word": "Cát Tường",
      "weith": "1"
    },
    {
      "word": "chém",
      "weith": "5"
    },
    {
      "word": "cướp",
      "weith": "1"
    },
    {
      "word": "cướp giật",
      "weith": "5"
    },
    {
      "word": "đãi vàng",
      "weith": "5"
    },
    {
      "word": "đánh chết",
      "weith": "4"
    },
    {
      "word": "đồng ý",
      "weith": "5"
    },
    {
      "word": "giết",
      "weith": "6"
    },
    {
      "word": "giết người",
      "weith": "1"
    },
    {
      "word": "He-rô-in",
      "weith": "2"
    },
    {
      "word": "hiếp dâm",
      "weith": "2"
    },
    {
      "word": "khổ sai",
      "weith": "5"
    },
    {
      "word": "khởi tố",
      "weith": "5"
    },
    {
      "word": "làm thuê",
      "weith": "5"
    },
    {
      "word": "Mường",
      "weith": "4"
    },
    {
      "word": "Nguyễn Mạnh Tường",
      "weith": "2"
    },
    {
      "word": "phi tang",
      "weith": "5"
    },
    {
      "word": "tạm giữ",
      "weith": "6"
    },
    {
      "word": "thu giữ",
      "weith": "2"
    },
    {
      "word": "trái phép",
      "weith": "3"
    },
    {
      "word": "trinh sát",
      "weith": "6"
    },
    {
      "word": "trở về",
      "weith": "5"
    },
    {
      "word": "trộm cắp",
      "weith": "2"
    },
    {
      "word": "vận chuyển",
      "weith": "6"
    },
    {
      "word": "xe SH",
      "weith": "3"
    },
    {
      "word": "xét xử",
      "weith": "1"
    }
  ]
}